gurobi/VERSION
gurobi/__init__.py
gurobi/__main__.py
gurobi/gurobi_check.py
gurobi_machines_plugin-0.7.0.data/data/VERSION/VERSION
gurobi_machines_plugin-0.7.0.dist-info/DESCRIPTION.rst
gurobi_machines_plugin-0.7.0.dist-info/METADATA
gurobi_machines_plugin-0.7.0.dist-info/RECORD
gurobi_machines_plugin-0.7.0.dist-info/WHEEL
gurobi_machines_plugin-0.7.0.dist-info/entry_points.txt
gurobi_machines_plugin-0.7.0.dist-info/metadata.json
gurobi_machines_plugin-0.7.0.dist-info/top_level.txt
