Metadata-Version: 2.0
Name: gurobi-machines-plugin
Version: 0.7.0
Summary: check gurobi machines actives for long time
Home-page: https://github.com/pablodav/gurobi_machines_plugin
Author: Pablo Estigarribia
Author-email: pablodav@gmail.com
License: MIT
Platform: UNKNOWN
Classifier: Development Status :: 5 - Production/Stable
Classifier: Intended Audience :: System Administrators
Classifier: License :: OSI Approved :: MIT License
Classifier: Programming Language :: Python :: 3
Classifier: Programming Language :: Python :: 3 :: Only
Classifier: Topic :: System :: Monitoring
Requires-Dist: arrow
Requires-Dist: requests (>=2.19.1)
Requires-Dist: rstcheck
